claude_logging/__init__.py
claude_logging/__main__.py
claude_logging/ansi2html.py
claude_logging/pytermdump.abi3.so
claude_logging/pytermdump.c
claude_logging/termdump.c
claude_logging-0.4.1.dist-info/LICENSE
claude_logging-0.4.1.dist-info/METADATA
claude_logging-0.4.1.dist-info/WHEEL
claude_logging-0.4.1.dist-info/entry_points.txt
claude_logging-0.4.1.dist-info/top_level.txt
claude_logging-0.4.1.dist-info/RECORD
