Metadata-Version: 2.1
Name: claude-logging
Version: 0.4.1
Summary: Save logs of claude code, and convert them into HTML
Author: Antonio Cuni
License: MIT
Project-URL: Homepage, https://github.com/antocuni/claude-logging
Project-URL: Bug Tracker, https://github.com/antocuni/claude-logging/issues
Keywords: claude,logging,ansi,terminal,html,conversion
Platform: UNKNOWN
Classifier: Programming Language :: Python :: 3
Classifier: Programming Language :: Python :: 3.8
Classifier: Programming Language :: Python :: 3.9
Classifier: Programming Language :: Python :: 3.10
Classifier: Programming Language :: Python :: 3.11
Classifier: Programming Language :: Python :: 3.12
Classifier: License :: OSI Approved :: MIT License
Classifier: Operating System :: OS Independent
Classifier: Intended Audience :: Developers
Classifier: Topic :: Software Development :: Libraries :: Python Modules
Classifier: Topic :: Terminals
Classifier: Topic :: Text Processing :: Markup :: HTML
Requires-Python: >=3.8
License-File: LICENSE
